[
  {
    "no": 16,
    "title": "test1",
    "description": "test1",
    "inDate": "01/24 11:12",
    "modifyDate": "01/24 11:12",
    "comments_length": 1,
    "hit": 2,
    "nickname": "백승범 일해라",
    "id": "agile1"
  },
  {
    "no": 21,
    "title": "백승범 일하라rr222r",
    "description": "일 안하는 백엔드 팀장 사퇴하라",
    "inDate": "01/24 11:18",
    "modifyDate": "01/24 11:18",
    "comments_length": 0,
    "hit": 0,
    "nickname": "백승범 일해라",
    "id": "agile1"
  },
  {
    "no": 25,
    "title": "today",
    "description": "아아아",
    "inDate": "01/24 14:18",
    "modifyDate": "01/24 14:18",
    "comments_length": 32,
    "hit": 12,
    "nickname": "백승범 일해라",
    "id": "agile1"
  },
  {
    "no": 26,
    "title": "test1",
    "description": "test1",
    "inDate": "01/24 15:09",
    "modifyDate": "01/24 15:09",
    "comments_length": 0,
    "hit": 16,
    "nickname": "백승범 일해라",
    "id": "agile1"
  },
  {
    "no": 27,
    "title": "test1",
    "description": "test1",
    "inDate": "01/24 15:23",
    "modifyDate": "01/24 15:23",
    "comments_length": 0,
    "hit": 4,
    "nickname": "백승범 일해라",
    "id": "agile1"
  },
  {
    "no": 28,
    "title": "test1",
    "description": "test1",
    "inDate": "01/24 15:23",
    "modifyDate": "01/24 15:23",
    "comments_length": 0,
    "hit": 0,
    "nickname": "백승범 일해라",
    "id": "agile1"
  },
  {
    "no": 29,
    "title": "test1",
    "description": "test1",
    "inDate": "01/24 15:23",
    "modifyDate": "01/24 15:23",
    "comments_length": 0,
    "hit": 0,
    "nickname": "백승범 일해라",
    "id": "agile1"
  },
  {
    "no": 30,
    "title": "test1",
    "description": "test1",
    "inDate": "01/24 15:24",
    "modifyDate": "01/24 15:24",
    "comments_length": 0,
    "hit": 0,
    "nickname": "백승범 일해라",
    "id": "agile1"
  },
  {
    "no": 31,
    "title": "test1",
    "description": "test1",
    "inDate": "01/24 15:27",
    "modifyDate": "01/24 15:27",
    "comments_length": 0,
    "hit": 0,
    "nickname": "백승범 일해라",
    "id": "agile1"
  },
  {
    "no": 32,
    "title": "test1",
    "description": "test1",
    "inDate": "01/24 15:27",
    "modifyDate": "01/24 15:27",
    "comments_length": 0,
    "hit": 0,
    "nickname": "백승범 일해라",
    "id": "agile1"
  },
  {
    "no": 33,
    "title": "test1",
    "description": "test1",
    "inDate": "01/24 15:27",
    "modifyDate": "01/24 15:27",
    "comments_length": 0,
    "hit": 0,
    "nickname": "백승범 일해라",
    "id": "agile1"
  }
]
